webscraper_lite/__init__.py
webscraper_lite/scraper.py
webscraper_lite-0.1.0.dist-info/METADATA
webscraper_lite-0.1.0.dist-info/WHEEL
webscraper_lite-0.1.0.dist-info/top_level.txt
webscraper_lite-0.1.0.dist-info/RECORD
