Metadata-Version: 2.4
Name: webscraper-lite
Version: 0.1.0
Summary: A simple Python web scraping utility
Home-page: https://github.com/yourusername/webscraper-lite
Author: Jay Telgote
Author-email: ijaytelgote@gmail.com
License: MIT
Requires-Python: >=3.7
Requires-Dist: requests
Requires-Dist: beautifulsoup4
Dynamic: author
Dynamic: author-email
Dynamic: description
Dynamic: description-content-type
Dynamic: home-page
Dynamic: license
Dynamic: requires-dist
Dynamic: requires-python
Dynamic: summary
